odoo/addons/edi_account_core_oca/README.rst
odoo/addons/edi_account_core_oca/__init__.py
odoo/addons/edi_account_core_oca/__manifest__.py
odoo/addons/edi_account_core_oca/hooks.py
odoo/addons/edi_account_core_oca/i18n/edi_account.pot
odoo/addons/edi_account_core_oca/i18n/edi_account_core_oca.pot
odoo/addons/edi_account_core_oca/i18n/edi_account_oca.pot
odoo/addons/edi_account_core_oca/i18n/fr.po
odoo/addons/edi_account_core_oca/i18n/it.po
odoo/addons/edi_account_core_oca/models/__init__.py
odoo/addons/edi_account_core_oca/models/account_move.py
odoo/addons/edi_account_core_oca/readme/CONTRIBUTORS.md
odoo/addons/edi_account_core_oca/readme/DESCRIPTION.md
odoo/addons/edi_account_core_oca/static/description/icon.png
odoo/addons/edi_account_core_oca/static/description/index.html
odoo/addons/edi_account_core_oca/views/account_journal.xml
odoo/addons/edi_account_core_oca/views/account_move.xml
odoo/addons/edi_account_core_oca/views/edi_exchange_record.xml
odoo/addons/edi_account_core_oca/views/res_partner.xml
odoo_addon_edi_account_core_oca-18.0.1.1.1.1.dist-info/METADATA
odoo_addon_edi_account_core_oca-18.0.1.1.1.1.dist-info/WHEEL
odoo_addon_edi_account_core_oca-18.0.1.1.1.1.dist-info/top_level.txt
odoo_addon_edi_account_core_oca-18.0.1.1.1.1.dist-info/RECORD
